[{"title": "Poquito A Poco", "artist": "Oro Negro"}, {"title": "Solo Importas Tu", "artist": "Franco de Vita"}, {"title": "LOVE", "artist": "Al Bano Y Romina Power"}, {"title": "Hasta Que Te Conoci", "artist": "Juan Gabriel"}, {"title": "Cuando La Lluvia Queme", "artist": "Glenn Monroig"}, {"title": "No Te Quites La Ropa", "artist": "Pedro Conga y Su Orquesta"}, {"title": "Toda la vida", "artist": "Emmanuel"}, {"title": "Donde estas amor", "artist": "Rocio Jurado"}, {"title": "Veneno Para Dos", "artist": "Daniela Romo"}, {"title": "Yo no se que me paso", "artist": "Juan Gabriel"}, {"title": "La Bamba", "artist": "Ritchie Valens"}, {"title": "Toda la vida", "artist": "July Mateo Rasputin"}, {"title": "Y TU TAMBIEN LLORARAS", "artist": "Jose Luis Rodriguez"}, {"title": "LA GALLINA", "artist": "Fito Olivares y Su Grupo"}, {"title": "Me Pase De La Cuenta", "artist": "Nelson Ned"}, {"title": "Estoy llorando", "artist": "Los Freddies"}, {"title": "Amigos", "artist": "Gerardo Reyes y Lorenzo de Monteclaro"}, {"title": "La Distancia", "artist": "Yesenia Florez"}, {"title": "Dicen", "artist": "La Revolucion De Emiliano Zapata"}, {"title": "Tu carcel", "artist": "Los Bukis"}, {"title": "De Pecho A Pecho", "artist": "Sonia Rivas"}, {"title": "AJA AJU", "artist": "Jose Nogueras"}, {"title": "Timido", "artist": "Flans"}, {"title": "MI NOVIA, MI AMANTE, MI MUJER", "artist": "Sandy Reyes"}, {"title": "Amada Mia", "artist": "Jose Luis Perales"}, {"title": "y quien puede ser", "artist": "Jose Jose"}, {"title": "Lloraras", "artist": "Los Hijos de Puerto Rico"}, {"title": "No me mires asi", "artist": "Manoella Torres y Los Diablos"}, {"title": "Salvame", "artist": "Wilfrido Vargas"}, {"title": "Los hijos de Hernandez", "artist": "Los Tigres del Norte"}, {"title": "Que no se rompa la noche", "artist": "Julio Iglesias"}, {"title": "Fuga", "artist": "Lissette"}, {"title": "Ahora Ahora", "artist": "Yolandita Monge"}, {"title": "Amar o morir", "artist": "Danny Rivera"}, {"title": "PONTE A CANTAR", "artist": "Jose Feliciano"}, {"title": "Otra semana", "artist": "Carmin"}, {"title": "Perdidos", "artist": "Oscar De Fontana"}, {"title": "Me Vas A Echar De Menos", "artist": "Willie Rosario"}, {"title": "Juguete de nadie", "artist": "Braulio"}, {"title": "Vivir lo nuestro", "artist": "Basilio"}, {"title": "No soy una muneca", "artist": "Rocio Banquells"}, {"title": "Lobo Domesticado", "artist": "Tommy Olivencia"}, {"title": "Y me decidi", "artist": "Jose Medina"}, {"title": "Plato de segunda mesa", "artist": "Hector LaVoe"}, {"title": "UNA ROSA Y UNA ESPINA", "artist": "Elio Roca"}, {"title": "Castigame", "artist": "Lucia Mendez"}, {"title": "Porque Tengo Ganas", "artist": "Marisela"}, {"title": "Ya No Volvare", "artist": "Laura Flores"}, {"title": "Amante Pasada De Moda", "artist": "Sussy Leman"}, {"title": "Pajaro que comio volo", "artist": "The New York Band"}, {"title": "La Bamba", "artist": "Los Lobos"}, {"title": "CORRE CORRE", "artist": "Flans"}, {"title": "La Pura Vida", "artist": "Braulio"}, {"title": "Soy", "artist": "Franco"}, {"title": "Paciencia", "artist": "Alejandro Jaen"}, {"title": "Decir te quiero", "artist": "Miguel Gallardo"}, {"title": "EL PECADO", "artist": "The New York Band"}, {"title": "Que locura enamorarme de ti", "artist": "Eddie Santiago"}, {"title": "Que Me Das", "artist": "Amanda Miguel"}, {"title": "Siga bailando", "artist": "Bonny Cepeda"}, {"title": "Baila conmigo", "artist": "Tatiana"}, {"title": "Todo Me Gusta De Ti", "artist": "Los Caminantes"}, {"title": "Contigo", "artist": "Yolandita Monge"}, {"title": "Luka", "artist": "Suzanne Vega"}, {"title": "NI GUERRA NI PAZ", "artist": "Lupita D'Alessio"}, {"title": "Te Estoy Hablando En Serio", "artist": "Lolita"}, {"title": "Cuando estes con el", "artist": "Wilfrido Vargas"}, {"title": "Desamor", "artist": "Laura Flores"}, {"title": "DEBO HACERLO", "artist": "Juan Gabriel"}, {"title": "Eva", "artist": "Lissette"}, {"title": "PARA NO PENSAR EN TI", "artist": "Napoleon"}, {"title": "Entre tu y yo", "artist": "Beatriz Adriana y Marco Antonio Solis"}, {"title": "Doce rosas", "artist": "Lorenzo Antonio"}, {"title": "Dos hombres y un destino", "artist": "Miguel Gallardo"}, {"title": "Sueltame", "artist": "Maria Conchita Alonso"}, {"title": "Siempre Siempre", "artist": "Al Bano Y Romina Power"}, {"title": "No renunciare", "artist": "Jorge Rigo"}, {"title": "Una Dama Y Un Senior", "artist": "Joan Sebastian & Prisma"}, {"title": "Como una mariposa", "artist": "Pandora"}, {"title": "Golpes bajos", "artist": "Dyango"}, {"title": "Hoy vine con ella", "artist": "Lissette y Manoella Torres"}, {"title": "Todavia duele", "artist": "Los Sabrosos del Merengue"}, {"title": "NO LO DEJES CAER", "artist": "JOHNNY VENTURA/SOPHY"}, {"title": "Cara o cruz", "artist": "Menudo"}, {"title": "Nena", "artist": "Miguel Bose"}, {"title": "A Falta De Ti", "artist": "Dyango"}, {"title": "No Me la LLame Mas", "artist": "Gilberto Santa Rosa"}, {"title": "Senorita", "artist": "Jose Medina"}, {"title": "Un nuevo amor", "artist": "Maria del Sol"}, {"title": "Tu tienes la culpa", "artist": "Sophy"}, {"title": "Yo No Soy Como Ave Mansa, No", "artist": "Luisa Maria Guel"}, {"title": "Muneca Rota", "artist": "Valeria Lynch"}, {"title": "Amigo Mio", "artist": "Jorge Muniz"}, {"title": "Por Eso", "artist": "Jose Feliciano"}, {"title": "Sin Saber", "artist": "Jose Jose"}, {"title": "La hora del adios", "artist": "Dyango y Rocio Durcal"}, {"title": "Girando Girando", "artist": "Maria del Sol"}, {"title": "Nadie mejor que tu", "artist": "Eddie Santiago"}, {"title": "Alguien llena mi lugar", "artist": "Pandora"}, {"title": "Cantante de cartel", "artist": "Gilberto Santa Rosa"}, {"title": "A ver si es de verdad", "artist": "Jose Alfredo Fuentes"}, {"title": "Yo no se quererte mas", "artist": "Lucia Mendez"}, {"title": "Por Quererme A Mi", "artist": "Dyango"}, {"title": "Por eso me voy", "artist": "Grupo El Tiempo"}, {"title": "Noche de boda", "artist": "Braulio"}, {"title": "No lo cambio por nada", "artist": "Angela Carrasco"}, {"title": "Maldito sea tu amor", "artist": "Estela Nunez"}, {"title": "De corazon a corazon", "artist": "Roberto Carlos"}, {"title": "Esa Mujer", "artist": "Jose Nogueras"}, {"title": "AUTOS, MODA Y ROCK AND ROLL", "artist": "Fandango USA"}, {"title": "HAZME OLVIDARLA", "artist": "Alvaro Torres"}, {"title": "Olvida tus penas", "artist": "Johnny Ventura"}, {"title": "Se me sigue olvidando", "artist": "Jose Feliciano"}, {"title": "Fuera de mi vida", "artist": "Valeria Lynch"}, {"title": "Me hace falta una flor", "artist": "Pimpinela"}, {"title": "Yo Me Voy Sola", "artist": "Lissette"}, {"title": "TU LUGAR, MI LUGAR", "artist": "Orquesta La Solucion"}, {"title": "La guirnalda", "artist": "Rocio Durcal"}, {"title": "Macumba", "artist": "Veronica Castro"}, {"title": "Cruz De Navajas", "artist": "Mecano"}, {"title": "SOY ASI", "artist": "Jose Jose"}, {"title": "Infidelidad", "artist": "Rocio Durcal"}, {"title": "LAMENTO DE SOLTERO", "artist": "Conjunto Quisqueya"}, {"title": "Era la primera vez", "artist": "Lucerito"}, {"title": "Quiero llenarte", "artist": "Franky Ruiz"}, {"title": "No Se Murio El Amor", "artist": "Mijares"}, {"title": "Negra", "artist": "Roberto Carlos"}, {"title": "Cancion", "artist": "Sonora Poncena"}, {"title": "Hasta cuando", "artist": "Beatriz Adriana"}, {"title": "Si vivir contigo", "artist": "Lunna"}, {"title": "La senora", "artist": "Claudia de Colombia"}, {"title": "Margarita", "artist": "Wilkins"}, {"title": "Garantia", "artist": "El Gran Combo de Puerto Rico"}, {"title": "Acariciame", "artist": "La Patrulla"}, {"title": "Ojo aja", "artist": "La Patrulla"}, {"title": "No Digas Nada", "artist": "Lunna"}, {"title": "Quien Te Crees Tu", "artist": "Rocio Jurado"}, {"title": "Manana al medio dia", "artist": "Gilberto Santa Rosa"}, {"title": "NO TIRES LA PRIMERA PIEDRA", "artist": "Tommy Olivencia"}, {"title": "El hombre de mi vida", "artist": "Angelica Maria"}, {"title": "No Es Igual", "artist": "Sussy Leman"}, {"title": "MIMA", "artist": "El Gran Combo de Puerto Rico"}, {"title": "Todo El Amor Que Te Hace Falta", "artist": "Julio Iglesias"}, {"title": "Golpeame", "artist": "Bonny Cepeda"}, {"title": "Capullo y Sorullo", "artist": "La Sonora Dinamita"}, {"title": "La Suavecita", "artist": "Junior Y Jorge Mandungo"}, {"title": "Tu Lugar Es Mi Lugar", "artist": "Los Iracundos"}, {"title": "Quedate conmigo esta noche", "artist": "Rocio Durcal"}, {"title": "Es mi mujer", "artist": "Emmanuel"}, {"title": "Bandolero", "artist": "Tatiana"}, {"title": "No quieren parar", "artist": "Jose Nogueras"}, {"title": "Hoy quiero confesarme", "artist": "Isabel Pantoja"}, {"title": "La luna sera la luna", "artist": "Beatriz Adriana"}, {"title": "Esta noche vendras", "artist": "Vikki Carr"}, {"title": "HOY NO QUIERO ESTAR SOLA", "artist": "Lourdes Robles"}, {"title": "Tu dama de hierro", "artist": "Marisela"}, {"title": "Que lastima", "artist": "Juan Gabriel"}, {"title": "Te pareces tanto a mi", "artist": "Orquesta Inmensidad"}, {"title": "Si tu eres mi hombre", "artist": "The New York Band"}, {"title": "El pecado", "artist": "Amanda Miguel"}, {"title": "Me la estas poniendo dificil", "artist": "Camilo Sesto"}, {"title": "Ojos De Color Cafe", "artist": "Bertin Osborne"}, {"title": "El Dolor De Tu Presencia", "artist": "Ednita Nazario"}, {"title": "Prohibido", "artist": "Angelica Maria"}, {"title": "Esta Noche Gano Yo", "artist": "Rocio Jurado"}, {"title": "SI TU ME DICES", "artist": "La Patrulla 15"}, {"title": "Corre y ve con el", "artist": "Jose Jose"}, {"title": "Solo el y yo", "artist": "Pandora"}, {"title": "QUE NO TE EXTRANE", "artist": "Vicente Fernandez"}, {"title": "La Isla Bonita", "artist": "Byanka"}, {"title": "La Coloreteada", "artist": "Los Hermanos Mier"}, {"title": "Si Te Preguntan", "artist": "Basilio"}, {"title": "Ahora Te Puedes Marchar", "artist": "Luis Miguel"}, {"title": "La quiero a morir", "artist": "Los Hijos del Rey"}, {"title": "Corazon Errante", "artist": "Estela Nunez"}, {"title": "luna de miel", "artist": "Paloma San Basilio"}, {"title": "Tu boca", "artist": "Oro Negro"}, {"title": "Tu sin mi", "artist": "Ednita Nazario"}, {"title": "Coco loco", "artist": "Daniela Romo"}, {"title": "No me vuelvo a enamorar", "artist": "Miami Sound Machine"}, {"title": "Quien Eres Tu", "artist": "Camilo Sesto"}, {"title": "Fiesta En America", "artist": "Chayanne"}, {"title": "POR ALGUIEN COMO TU", "artist": "Ilan Chester"}, {"title": "De mi enamorate", "artist": "Daniela Romo"}, {"title": "Vivir Sin Ti", "artist": "Yuri"}, {"title": "PETALO Y ESPINAS", "artist": "Los Yonic's"}, {"title": "Corazon vacio", "artist": "Los Yonic's"}, {"title": "Soy lo peor", "artist": "Rubby Haddock"}, {"title": "Solo", "artist": "Emmanuel"}, {"title": "La Fotografia", "artist": "Bonny Cepeda"}, {"title": "La Gosadera", "artist": "Conjunto Quisqueya"}, {"title": "Otra Mentira Mas", "artist": "Maria Conchita Alonso"}, {"title": "La hierva se movia", "artist": "Tropicalisimo Apache"}, {"title": "Lobo domesticado", "artist": "Joan Sebastian"}, {"title": "No Te Quites La Ropa", "artist": "Emmanuel"}, {"title": "Lastima De Amor", "artist": "Los Yonic's"}, {"title": "Extranjera", "artist": "Miguel Gallardo"}, {"title": "Celos", "artist": "Pedro Pardo"}, {"title": "Tan solo necesito", "artist": "Jose Luis Perales"}, {"title": "A FUEGO LENTO", "artist": "Grupo El Tiempo"}, {"title": "Duele", "artist": "Basilio"}, {"title": "No me toques", "artist": "Carla"}, {"title": "Lo Mejor De Tu Vida", "artist": "Julio Iglesias"}, {"title": "Mi Hombre", "artist": "Pandora"}, {"title": "DOS CORAZONES", "artist": "Vicente Fernandez/Vikki Carr"}, {"title": "Sera El Angel", "artist": "Lisa Lopez"}, {"title": "IMPOSIBLE AMOR", "artist": "Franky Ruiz"}, {"title": "Es ella mas que yo", "artist": "Yuri"}, {"title": "Arrepentida", "artist": "Marisela"}, {"title": "Hay Que Pesado", "artist": "Mecano"}, {"title": "Hoy platique con mi gallo", "artist": "Vicente Fernandez"}, {"title": "Ladrona De Amor", "artist": "Jorge Rigo"}, {"title": "Aqui estas otra vez", "artist": "Franco de Vita"}, {"title": "AY AMOR", "artist": "Ana Gabriel"}, {"title": "Siempre", "artist": "Rocio Durcal"}, {"title": "Te Estas Pasando", "artist": "Lupita D'Alessio"}, {"title": "Te amare", "artist": "Jose Feliciano"}, {"title": "No Me Puedo Ecapar", "artist": "Rocio Banquells/Luis Miguel"}, {"title": "Amor Caliente", "artist": "Dulce"}, {"title": "Fugitivo amante", "artist": "Lunna"}, {"title": "Hoy Por Ti Manana Por Mi", "artist": "Flans"}, {"title": "LLUVIA", "artist": "Eddie Santiago"}, {"title": "HAZME TUYA", "artist": "Marisela"}, {"title": "Este adios", "artist": "Los Bukis"}, {"title": "Te Quiero, Te Quiero", "artist": "La Patrulla 15"}, {"title": "Hasta Que Te Conoci", "artist": "Roberto del Castillo"}, {"title": "Nunca Fui", "artist": "El Gran Combo de Puerto Rico"}, {"title": "Alma De Gitana", "artist": "Ednita Nazario"}, {"title": "DESAYUNO DE AMOR", "artist": "Brenda K. Starr"}, {"title": "La Bamba", "artist": "Selena y Los Dinos"}, {"title": "A cual piso", "artist": "Johnny Ventura"}, {"title": "Se Acabo El Pan De Piquito", "artist": "Ismael Miranda"}, {"title": "De color de rosa", "artist": "Prisma"}, {"title": "Si yo fuera mujer", "artist": "Wilkins"}, {"title": "Ven a cantar", "artist": "La Hermandad"}, {"title": "Cuando termine el amor", "artist": "Wilkins"}, {"title": "Oiga", "artist": "Joan Sebastian & Prisma"}, {"title": "Me la estas poniendo dificil", "artist": "Andy Montanez"}, {"title": "Me estoy volviendo loco", "artist": "Jose Javier Solis"}, {"title": "Muriendo Aqui", "artist": "Franco"}, {"title": "Laberinto", "artist": "Yolandita Monge"}, {"title": "Adios que te vaya bien", "artist": "Mario Pintor"}, {"title": "En bancarrota", "artist": "Braulio"}, {"title": "CUARTO DE HOTEL 303", "artist": "Bonny Cepeda"}, {"title": "Toda la vida", "artist": "Franco"}, {"title": "Te Prometo", "artist": "Carlos Alfredo"}, {"title": "Corazon herido", "artist": "Yuri"}, {"title": "Me Volvi A Acordar De Ti", "artist": "Los Bukis"}, {"title": "Besos de ceniza", "artist": "Timbiriche"}, {"title": "Te quiero tanto", "artist": "Jochi Hernandez"}, {"title": "Desnudate mujer", "artist": "Franky Ruiz"}, {"title": "Cole", "artist": "The New York Band"}, {"title": "El senor de la senora", "artist": "Bobby Valentin"}, {"title": "Se Como Duele", "artist": "Karina"}]