[{"title": "Entre Tu Y Yo", "artist": "Jyve V", "yt_id": "GoZQw-1Eqj8"}, {"title": "Bano De Luna", "artist": "Melina Leon", "yt_id": "iRt5BaPHhMo"}, {"title": "Y Dale", "artist": "Limi-T 21", "yt_id": "m1JgtkCziHg"}, {"title": "A Ella", "artist": "El Poder del Norte", "yt_id": "t4oLtO1ZmWA"}, {"title": "Cancion En La Arena", "artist": "Fiel A La Vega", "yt_id": "hs8YNJXopYc"}, {"title": "Yo Se Que Te Acordaras", "artist": "Banda El Recodo de Cruz Lizarraga", "yt_id": "isxFPAxmJXs"}, {"title": "No Me Dejes De Querer", "artist": "Gloria Estefan", "yt_id": "EtUMbMD4Mv4"}, {"title": "Como Duele", "artist": "Victor Manuelle", "yt_id": "AnZ8p9k1hZg"}, {"title": "Sin Ti No Se Vivir", "artist": "Los Angeles Azules", "yt_id": "zLAROpnv8ok"}, {"title": "Sentirme Vivo", "artist": "Emmanuel", "yt_id": "31WGs_lfLxY"}, {"title": "Solo Un Recuerdo", "artist": "Los Huracanes del Norte", "yt_id": "SHKhz9JAy2k"}, {"title": "Que Voy A Hacer Sin Ti", "artist": "Pablo Montero", "yt_id": "VcjzENmgHwY"}, {"title": "Soy Un Sabordin", "artist": "Marco Hernandez", "yt_id": "IgOH7wjN4RM"}, {"title": "Por Tu Amor", "artist": "Charlie Zaa", "yt_id": "Ewt3mEUBD4E"}, {"title": "No Te Cambio Por Ninguna", "artist": "Luis Fonsi", "yt_id": "ejspImi_-2o"}, {"title": "Pideme", "artist": "Milly Quezada With Fernandito Villalona", "yt_id": "_JCvwb9fbac"}, {"title": "Donde E' Que E'", "artist": "Fernando Echavarria", "yt_id": "VhA_dPRKAIw"}, {"title": "Tao Tao", "artist": "Control", "yt_id": "3M9RahnD7ZE"}, {"title": "Y...", "artist": "Luis Miguel", "yt_id": "LK6UmfC8N6E"}, {"title": "Que Se Yo", "artist": "Luis Enrique", "yt_id": "_igYGOAhXWk"}, {"title": "En Toda La Chapa", "artist": "Banda Machos", "yt_id": "JrIqyKxe_YQ"}, {"title": "Para Poder Llegar A Ti", "artist": "Julio Preciado Y Su Banda Perla del Pacifico", "yt_id": "BO0knYxvwk0"}, {"title": "Ojos Negros", "artist": "Ricardo Montaner Con La London Metropolitan Orchestra", "yt_id": "uewAqzKc7zk"}, {"title": "Estas Enamorada", "artist": "Patrick Shannon", "yt_id": "KOCVguQIpfw"}, {"title": "De Creer En Ti [On My Knees]", "artist": "Jaci Velasquez", "yt_id": "mFmbD8DF-a8"}, {"title": "No Creo", "artist": "Shakira", "yt_id": "cNIJCqmUlJI"}, {"title": "Dime, Dime, Dime", "artist": "Conjunto Primavera", "yt_id": "dAhMQEKf05k"}, {"title": "Ando Amanecido", "artist": "Los Tigres del Norte", "yt_id": "AiALQ6AnVY4"}, {"title": "El Coyote", "artist": "Oro Norteno", "yt_id": "EWvl6QaXtfo"}, {"title": "Abrazame Muy Fuerte", "artist": "Juan Gabriel", "yt_id": "_tNVEhSelH0"}, {"title": "Yo Te Amo", "artist": "Chayanne", "yt_id": "YkVbgpXXR0M"}, {"title": "Como Me Duele Perderte", "artist": "Gloria Estefan", "yt_id": "O4nFvS9j4Rg"}, {"title": "La Ladrona", "artist": "Ilegales", "yt_id": "ayQ2ZYZtXFQ"}, {"title": "Te Quise Olvidar", "artist": "MDO", "yt_id": "Jd86fMKwtGg"}, {"title": "Secreto de Amor", "artist": "Joan Sebastian", "yt_id": "loduYZcFRtE"}, {"title": "Lobo Herido", "artist": "Vicente Fernandez", "yt_id": "s4OaXneowIA"}, {"title": "Donde Esta El Amor", "artist": "Charlie Zaa", "yt_id": "zxLsPEYotsc"}, {"title": "El Original", "artist": "Los Originales de San Juan", "yt_id": "85wVF82ozBQ"}, {"title": "Te Hice Mal", "artist": "Los Temerarios", "yt_id": "0K-WctIjMhk"}, {"title": "Ayudame Dios Mio", "artist": "Tamara", "yt_id": "_1_V-jXrnbQ"}, {"title": "Come Baby Come", "artist": "Gizelle D'Cole Con Elvis Crespo", "yt_id": "o4J-yPsvTv4"}, {"title": "Yo Te Voy A Amar [This I Promise You]", "artist": "*NSYNC", "yt_id": "6thmPrTxBtI"}, {"title": "My Baby You", "artist": "Marc Anthony", "yt_id": "K3lbmgyp18o"}, {"title": "Cuando", "artist": "Ricardo Arjona", "yt_id": "Ks2TiFtBOwk"}, {"title": "Domingo Busca Un Amor", "artist": "Domingo Quinones", "yt_id": "ajROMMETfJ0"}, {"title": "Espero Que Te Cumpla", "artist": "Los Invasores de Nuevo Leon", "yt_id": "sbY4GIrZgns"}, {"title": "Sola", "artist": "India", "yt_id": "sajz8ASOjJI"}, {"title": "El Ultimo Beso", "artist": "Rayito Colombiano", "yt_id": "gIYaGpU6PXs"}, {"title": "Fuego En La Cintura", "artist": "Gisselle", "yt_id": "HAWTSmamwZ8"}, {"title": "A Escondidas", "artist": "Emanuel Ortega", "yt_id": "E6AaIdNS-d0"}, {"title": "Para Que Quieres Que Vuelva", "artist": "Polo Urias y Su Maquina Nortena", "yt_id": "OLREWL_S04o"}, {"title": "She Bangs", "artist": "Ricky Martin", "yt_id": "5ihtX86JzmA"}, {"title": "Me Traes De Un Ala", "artist": "Banda La Costena", "yt_id": "FTFoDYE8KtI"}, {"title": "Ensename A Olvidarte", "artist": "Intocable", "yt_id": "Bj4LlggJpVc"}, {"title": "Que Locura Enamorarme De Ti", "artist": "Eddie Santiago Y Huey Dunbar", "yt_id": "ntVxaVTfj3Y"}, {"title": "Infiel", "artist": "Rocio Durcal", "yt_id": "nGp4bu0PiUM"}, {"title": "Dormir Contigo", "artist": "Luis Miguel", "yt_id": "dkN7p0A9m6w"}, {"title": "La Palma", "artist": "Ezequiel Pena", "yt_id": "UsVDrLfSNKY"}, {"title": "Tus Caderas Te Traicionan", "artist": "Los Originales de San Juan", "yt_id": "FOcmZWDfqIk"}, {"title": "En Cada Gota De Mi Sangre", "artist": "Conjunto Primavera", "yt_id": "t8g0GEgG5Vc"}, {"title": "Tu Y Las Nubes", "artist": "Lupillo Rivera", "yt_id": "iOw-bg0tLQc"}, {"title": "Muy Dentro De Mi [You Sang To Me]", "artist": "Marc Anthony", "yt_id": "5S9Y2zBZmz0"}, {"title": "Desde Que No Estas", "artist": "Rey Ruiz", "yt_id": "PGAYkP1lopE"}, {"title": "Carita De Sol", "artist": "Tony Vega", "yt_id": "QAd0dtDenWM"}, {"title": "Tu Amor Eterno", "artist": "Carlos Vives", "yt_id": "kUsCwMejvPE"}, {"title": "Navidad Sin Ti", "artist": "Los Bukis", "yt_id": "Qg6RYiH4Ipo"}, {"title": "Que Sera", "artist": "Diego Torres", "yt_id": "KQABHXhMsvw"}, {"title": "Pegame Tu Vicio", "artist": "Eddy Herrera", "yt_id": "yWSQxGppcFA"}, {"title": "Cuando Una Mujer", "artist": "Melina Leon", "yt_id": "XqAH5hQADnk"}, {"title": "Cuando El Amor Se Dana", "artist": "Rikarena", "yt_id": "j4rljLJXiK0"}, {"title": "Entre Tu Y Mil Mares", "artist": "Laura Pausini", "yt_id": "w3JoAPJu7ho"}, {"title": "Deja", "artist": "Banda El Recodo de Cruz Lizarraga"}, {"title": "Entre El Mar Y Una Estrella", "artist": "Thalia"}, {"title": "Fuego En El Fuego", "artist": "Eros Ramazzotti"}, {"title": "Por La Espalda", "artist": "Banda La Costena"}, {"title": "El Diablo En Una Botella", "artist": "Voces del Rancho"}, {"title": "Corazon Esteril", "artist": "Pepe Aguilar"}, {"title": "Tus Reproches", "artist": "Los Sementales De Nuevo Leon"}, {"title": "Falsas Ilusiones", "artist": "Los Huracanes del Norte"}, {"title": "Que Mas Tu Quieres De Mi", "artist": "Tito Rojas"}, {"title": "Quisiera Ser", "artist": "Alejandro Sanz"}, {"title": "Se Va El Amor", "artist": "Los Tri-o"}, {"title": "Jurame", "artist": "Gisselle"}, {"title": "Cuando Nadie Me Ve", "artist": "Alejandro Sanz"}, {"title": "En Que Trabaja El Muchacho", "artist": "Los Huracanes del Norte"}, {"title": "Wow Flash!", "artist": "Elvis Crespo"}, {"title": "Me Gusta Vivir De Noche", "artist": "Los Tucanes de Tijuana"}, {"title": "Ven Conmigo (Solamente Tu) [Come On Over Baby (All I Want Is You)]", "artist": "Christina Aguilera"}, {"title": "Asi [Stop]", "artist": "Jon Secada"}, {"title": "Mentirosa", "artist": "Los Rieleros del Norte"}, {"title": "Como Tu Me Quiere' A Mi", "artist": "Limi-T 21"}, {"title": "De Paisano A Paisano", "artist": "Los Tigres del Norte"}, {"title": "Poema De Amor", "artist": "Renan Almendarez Coello"}, {"title": "Tres Regalos", "artist": "Vicente Fernandez"}, {"title": "Pa' Que Son Pasiones", "artist": "Tiranos del Norte"}, {"title": "Muevelo", "artist": "Rey Ruiz"}, {"title": "Yo Te Confieso", "artist": "Anthony"}, {"title": "Si No Te Hubieras Ido", "artist": "Charlie Cruz"}, {"title": "Oops!...I Did It Again", "artist": "Britney Spears"}, {"title": "Desnuda", "artist": "Ricardo Arjona"}, {"title": "Si La Ves", "artist": "Victor Manuelle"}, {"title": "Regresa A Mi", "artist": "Thalia"}, {"title": "Morir De Amor", "artist": "Conjunto Primavera"}, {"title": "Mujer, Mujer", "artist": "Los Traviezos del Norte"}, {"title": "Por Siempre Tu [I Turn To You]", "artist": "Christina Aguilera"}, {"title": "Como Este Loco", "artist": "Julio Preciado Y Su Banda Perla del Pacifico"}, {"title": "Corazon De Melao", "artist": "Emmanuel"}, {"title": "Ingrata Suerte", "artist": "Masizzo"}, {"title": "Volver A Amar", "artist": "Cristian"}, {"title": "Y Sigues Siendo Tu [You're Still The One]", "artist": "Rogelio Martinez \"EL RM\""}, {"title": "El Ultimo Adios", "artist": "Paulina Rubio"}, {"title": "Eras Todo Para Mi", "artist": "Los Temerarios"}, {"title": "Te Sone", "artist": "El Coyote y Su Banda Tierra Santa"}, {"title": "Quemame Los Ojos", "artist": "Ramon Ayala y Sus Bravos del Norte"}, {"title": "Ven A Mi [Run To Me]", "artist": "Oscar De La Hoya"}, {"title": "Un Lugar Celestial", "artist": "Jaci Velasquez"}, {"title": "Mi Primer Amor", "artist": "Kevin Ceballo"}, {"title": "Gozar La Vida", "artist": "Julio Iglesias"}, {"title": "Acariciame", "artist": "Limite"}, {"title": "Un Sueno", "artist": "Los Angeles de Charly"}, {"title": "Cachito", "artist": "Mana"}, {"title": "Que Sepan Todos", "artist": "Pepe Aguilar"}, {"title": "Mi Nina", "artist": "Los Toros Band"}, {"title": "Fuerte No Soy", "artist": "Intocable"}, {"title": "Casi Perfecta", "artist": "Michael Stuart"}, {"title": "Por Encima De Todo", "artist": "Limite"}, {"title": "Cuando Seas Mia", "artist": "Son By Four"}, {"title": "Lloran Las Rosas", "artist": "Dominic"}, {"title": "No Puedo Olvidar Tu Voz", "artist": "El Coyote y Su Banda Tierra Santa"}, {"title": "Remolino", "artist": "Frankie Negron"}, {"title": "Te Esperare", "artist": "Grupo Mateo's"}, {"title": "Ya Estoy Cansado", "artist": "Intocable"}, {"title": "Si Te Vas", "artist": "Alejandro Fernandez"}, {"title": "La Bomba", "artist": "Azul Azul"}, {"title": "Basura", "artist": "Los Mismos"}, {"title": "Busca Otro Amor", "artist": "Polo Urias y Su Maquina Nortena"}, {"title": "Los Dos Zacatecanos", "artist": "Banda Machos"}, {"title": "Por Que Me Enamore?", "artist": "Grupo Bryndis"}, {"title": "A Puro Dolor", "artist": "Son By Four"}, {"title": "Amiga Mia", "artist": "Limite"}, {"title": "Quiereme", "artist": "Alejandro Fernandez"}, {"title": "Amarte Es Un Problema", "artist": "Charlie Cruz"}, {"title": "Imaginame Sin Ti [Imagine Me Without You]", "artist": "Luis Fonsi"}, {"title": "Donde Esta La Vida", "artist": "Francisco Cespedes"}, {"title": "Sin Alma", "artist": "Patricia Navidad"}, {"title": "Amor Secreto", "artist": "Los Angeles de Charly"}, {"title": "Las Heladas", "artist": "Los Tucanes de Tijuana"}, {"title": "Te Suplique Muchas Veces", "artist": "Banda Arkangel R-15"}, {"title": "Prision De Amor", "artist": "Los Tigres del Norte"}, {"title": "Porque Te Quiero", "artist": "Rocio Durcal"}, {"title": "Por Una Mujer Bonita", "artist": "Pepe Aguilar"}, {"title": "Borracho Te Recuerdo", "artist": "Vicente Fernandez"}, {"title": "Porque Te Quise", "artist": "Joan Sebastian"}, {"title": "Enloqueceme", "artist": "OV7"}, {"title": "Solo Me Importas Tu [Be With You]", "artist": "Enrique Iglesias"}, {"title": "Sufro", "artist": "El Coyote y Su Banda Tierra Santa"}, {"title": "Me Caiste Del Cielo", "artist": "Julio Preciado Y Su Banda Perla del Pacifico"}, {"title": "Sin Tu Amor", "artist": "Pedro Fernandez"}, {"title": "La Razon De Mi Ser", "artist": "Carlos Ponce"}, {"title": "Enamorado De Ti", "artist": "Frankie Negron"}, {"title": "Lo Hare Por Ti", "artist": "Paulina Rubio"}, {"title": "Que Bonito Amor", "artist": "Banda Maguey"}, {"title": "Historia Entre Tus Dedos", "artist": "Mickey Taveras"}, {"title": "Como Le Hago", "artist": "Pesado"}, {"title": "Inventame", "artist": "Marco Antonio Solis"}, {"title": "Por Amarte Asi", "artist": "Cristian"}, {"title": "Amarte Es Un Placer", "artist": "Luis Miguel"}, {"title": "Me Llamo Raquel", "artist": "Banda Machos"}, {"title": "Pena Tras Pena", "artist": "Banda El Recodo de Cruz Lizarraga"}, {"title": "La Bikina", "artist": "Luis Miguel"}, {"title": "Da La Vuelta", "artist": "Marc Anthony"}]